resourcemap/__init__.py
resourcemap/exceptions.py
resourcemap/warnings.py
resourcemap/core/__init__.py
resourcemap/core/__init__.pyi
resourcemap/core/format.py
resourcemap/core/format.pyi
resourcemap/core/load.py
resourcemap/core/load.pyi
resourcemap/core/locate.py
resourcemap/core/locate.pyi
resourcemap/core/py.typed
resourcemap/core/resource.py
resourcemap/core/resource.pyi
resourcemap-0.0.1.dist-info/METADATA
resourcemap-0.0.1.dist-info/WHEEL
resourcemap-0.0.1.dist-info/top_level.txt
resourcemap-0.0.1.dist-info/RECORD
