Metadata-Version: 2.4
Name: resourcemap
Version: 0.0.1
Summary: Python package that allows you to use application resources without worrying about where they are stored.
Author-email: quote-meta <nullpo.loveletter.vbs@gmail.com>
License-Expression: Apache-2.0
Classifier: Programming Language :: Python
Classifier: Programming Language :: Python :: 3
Classifier: Programming Language :: Python :: 3.12
Classifier: Operating System :: OS Independent
Classifier: Development Status :: 3 - Alpha
Classifier: Intended Audience :: Developers
Classifier: Topic :: Software Development :: Libraries :: Python Modules
Requires-Python: >=3.12
Requires-Dist: appdirs
Requires-Dist: pydantic
Requires-Dist: charset-normalizer
Provides-Extra: ipykernel
Requires-Dist: ipykernel; extra == "ipykernel"
Provides-Extra: yaml
Requires-Dist: PyYAML; extra == "yaml"
Provides-Extra: dev
Requires-Dist: pytest; extra == "dev"
Requires-Dist: pytest-mock; extra == "dev"
Requires-Dist: build; extra == "dev"
Requires-Dist: twine; extra == "dev"
